[
  {
    "login": "PatrickJS",
    "id": 1016365,
    "node_id": "MDQ6VXNlcjEwMTYzNjU=",
    "avatar_url": "https://avatars.githubusercontent.com/u/1016365?v=4",
    "gravatar_id": "",
    "url": "https://api.github.com/users/PatrickJS",
    "html_url": "https://github.com/PatrickJS",
    "followers_url": "https://api.github.com/users/PatrickJS/followers",
    "following_url": "https://api.github.com/users/PatrickJS/following{/other_user}",
    "gists_url": "https://api.github.com/users/PatrickJS/gists{/gist_id}",
    "starred_url": "https://api.github.com/users/PatrickJS/starred{/owner}{/repo}",
    "subscriptions_url": "https://api.github.com/users/PatrickJS/subscriptions",
    "organizations_url": "https://api.github.com/users/PatrickJS/orgs",
    "repos_url": "https://api.github.com/users/PatrickJS/repos",
    "events_url": "https://api.github.com/users/PatrickJS/events{/privacy}",
    "received_events_url": "https://api.github.com/users/PatrickJS/received_events",
    "type": "User",
    "user_view_type": "public",
    "site_admin": false,
    "name": "PatrickJS",
    "company": "@kunai-consulting",
    "blog": "patrickjs.com",
    "location": "California",
    "email": "github@patrickjs.com",
    "hireable": true,
    "bio": "building Web Scale and Open-Source\r\n\r\nCurrently: Consulting and Qwik (core team)\r\n\r\nPreviously: Angular, Angular Universal, Webpack, Falcor, Mitosis",
    "twitter_username": "PatrickJS__",
    "public_repos": 959,
    "public_gists": 303,
    "followers": 3202,
    "following": 379,
    "created_at": "2011-08-31T07:43:17Z",
    "updated_at": "2025-04-19T00:08:09Z"
  },
  {
    "login": "nabrams",
    "id": 12763153,
    "node_id": "MDQ6VXNlcjEyNzYzMTUz",
    "avatar_url": "https://avatars.githubusercontent.com/u/12763153?v=4",
    "gravatar_id": "",
    "url": "https://api.github.com/users/nabrams",
    "html_url": "https://github.com/nabrams",
    "followers_url": "https://api.github.com/users/nabrams/followers",
    "following_url": "https://api.github.com/users/nabrams/following{/other_user}",
    "gists_url": "https://api.github.com/users/nabrams/gists{/gist_id}",
    "starred_url": "https://api.github.com/users/nabrams/starred{/owner}{/repo}",
    "subscriptions_url": "https://api.github.com/users/nabrams/subscriptions",
    "organizations_url": "https://api.github.com/users/nabrams/orgs",
    "repos_url": "https://api.github.com/users/nabrams/repos",
    "events_url": "https://api.github.com/users/nabrams/events{/privacy}",
    "received_events_url": "https://api.github.com/users/nabrams/received_events",
    "type": "User",
    "user_view_type": "public",
    "site_admin": false,
    "name": "Natalie Abrams",
    "company": "@candidco ",
    "blog": "",
    "location": null,
    "email": null,
    "hireable": null,
    "bio": null,
    "twitter_username": null,
    "public_repos": 32,
    "public_gists": 0,
    "followers": 2,
    "following": 1,
    "created_at": "2015-06-05T13:27:52Z",
    "updated_at": "2025-04-30T22:17:34Z"
  },
  {
    "login": "thejackshelton",
    "id": 104264123,
    "node_id": "U_kgDOBjbxuw",
    "avatar_url": "https://avatars.githubusercontent.com/u/104264123?v=4",
    "gravatar_id": "",
    "url": "https://api.github.com/users/thejackshelton",
    "html_url": "https://github.com/thejackshelton",
    "followers_url": "https://api.github.com/users/thejackshelton/followers",
    "following_url": "https://api.github.com/users/thejackshelton/following{/other_user}",
    "gists_url": "https://api.github.com/users/thejackshelton/gists{/gist_id}",
    "starred_url": "https://api.github.com/users/thejackshelton/starred{/owner}{/repo}",
    "subscriptions_url": "https://api.github.com/users/thejackshelton/subscriptions",
    "organizations_url": "https://api.github.com/users/thejackshelton/orgs",
    "repos_url": "https://api.github.com/users/thejackshelton/repos",
    "events_url": "https://api.github.com/users/thejackshelton/events{/privacy}",
    "received_events_url": "https://api.github.com/users/thejackshelton/received_events",
    "type": "User",
    "user_view_type": "public",
    "site_admin": false,
    "name": "Jack Shelton",
    "company": null,
    "blog": "jackshelton.com",
    "location": "Dallas, TX",
    "email": null,
    "hireable": null,
    "bio": "Sharing the joy of fast and beautiful web experiences.",
    "twitter_username": "TheJackShelton",
    "public_repos": 179,
    "public_gists": 0,
    "followers": 41,
    "following": 14,
    "created_at": "2022-04-23T13:56:55Z",
    "updated_at": "2025-03-30T05:19:15Z"
  },
  {
    "login": "toan-kunaico",
    "id": 122486240,
    "node_id": "U_kgDOB0z94A",
    "avatar_url": "https://avatars.githubusercontent.com/u/122486240?v=4",
    "gravatar_id": "",
    "url": "https://api.github.com/users/toan-kunaico",
    "html_url": "https://github.com/toan-kunaico",
    "followers_url": "https://api.github.com/users/toan-kunaico/followers",
    "following_url": "https://api.github.com/users/toan-kunaico/following{/other_user}",
    "gists_url": "https://api.github.com/users/toan-kunaico/gists{/gist_id}",
    "starred_url": "https://api.github.com/users/toan-kunaico/starred{/owner}{/repo}",
    "subscriptions_url": "https://api.github.com/users/toan-kunaico/subscriptions",
    "organizations_url": "https://api.github.com/users/toan-kunaico/orgs",
    "repos_url": "https://api.github.com/users/toan-kunaico/repos",
    "events_url": "https://api.github.com/users/toan-kunaico/events{/privacy}",
    "received_events_url": "https://api.github.com/users/toan-kunaico/received_events",
    "type": "User",
    "user_view_type": "public",
    "site_admin": false,
    "name": null,
    "company": null,
    "blog": "",
    "location": null,
    "email": null,
    "hireable": null,
    "bio": null,
    "twitter_username": null,
    "public_repos": 3,
    "public_gists": 0,
    "followers": 0,
    "following": 0,
    "created_at": "2023-01-11T20:17:36Z",
    "updated_at": "2025-03-11T18:18:26Z"
  },
  {
    "login": "zaynet",
    "id": 2697335,
    "node_id": "MDQ6VXNlcjI2OTczMzU=",
    "avatar_url": "https://avatars.githubusercontent.com/u/2697335?v=4",
    "gravatar_id": "",
    "url": "https://api.github.com/users/zaynet",
    "html_url": "https://github.com/zaynet",
    "followers_url": "https://api.github.com/users/zaynet/followers",
    "following_url": "https://api.github.com/users/zaynet/following{/other_user}",
    "gists_url": "https://api.github.com/users/zaynet/gists{/gist_id}",
    "starred_url": "https://api.github.com/users/zaynet/starred{/owner}{/repo}",
    "subscriptions_url": "https://api.github.com/users/zaynet/subscriptions",
    "organizations_url": "https://api.github.com/users/zaynet/orgs",
    "repos_url": "https://api.github.com/users/zaynet/repos",
    "events_url": "https://api.github.com/users/zaynet/events{/privacy}",
    "received_events_url": "https://api.github.com/users/zaynet/received_events",
    "type": "User",
    "user_view_type": "public",
    "site_admin": false,
    "name": "Oleksandr Zainetdinov",
    "company": null,
    "blog": "",
    "location": "Kharkiv, Ukraine",
    "email": null,
    "hireable": null,
    "bio": null,
    "twitter_username": null,
    "public_repos": 2,
    "public_gists": 0,
    "followers": 5,
    "following": 5,
    "created_at": "2012-11-01T08:18:59Z",
    "updated_at": "2025-04-15T15:27:55Z"
  },
  {
    "login": "jay-kunaico",
    "id": 94001747,
    "node_id": "U_kgDOBZpaUw",
    "avatar_url": "https://avatars.githubusercontent.com/u/94001747?v=4",
    "gravatar_id": "",
    "url": "https://api.github.com/users/jay-kunaico",
    "html_url": "https://github.com/jay-kunaico",
    "followers_url": "https://api.github.com/users/jay-kunaico/followers",
    "following_url": "https://api.github.com/users/jay-kunaico/following{/other_user}",
    "gists_url": "https://api.github.com/users/jay-kunaico/gists{/gist_id}",
    "starred_url": "https://api.github.com/users/jay-kunaico/starred{/owner}{/repo}",
    "subscriptions_url": "https://api.github.com/users/jay-kunaico/subscriptions",
    "organizations_url": "https://api.github.com/users/jay-kunaico/orgs",
    "repos_url": "https://api.github.com/users/jay-kunaico/repos",
    "events_url": "https://api.github.com/users/jay-kunaico/events{/privacy}",
    "received_events_url": "https://api.github.com/users/jay-kunaico/received_events",
    "type": "User",
    "user_view_type": "public",
    "site_admin": false,
    "name": "Jay Brass",
    "company": null,
    "blog": "",
    "location": null,
    "email": null,
    "hireable": null,
    "bio": null,
    "twitter_username": null,
    "public_repos": 6,
    "public_gists": 0,
    "followers": 0,
    "following": 2,
    "created_at": "2021-11-09T16:02:56Z",
    "updated_at": "2024-05-01T13:26:58Z"
  }
]